setup.py
src/tj_text/__init__.py
src/tj_text/tjtext_preproc_ds.py
tjtext_preproc_ds-0.1.0.dist-info/METADATA
tjtext_preproc_ds-0.1.0.dist-info/WHEEL
tjtext_preproc_ds-0.1.0.dist-info/licenses/LICENSE
tjtext_preproc_ds-0.1.0.dist-info/RECORD
