Metadata-Version: 2.1
Name: tjtext_preproc_ds
Version: 0.1.0
Summary: An NLP text preprocessing function package
Project-URL: Homepage, https://github.com/tariqjamil-bwp/pypi_projects/
Project-URL: Bug Tracker, https://github.com/tariqjamil-bwp/pypi_projects/issues
Author-email: Tariq Jamil <tariqjamil.bwp@gmail.com>
License-File: LICENSE
Classifier: License :: OSI Approved :: MIT License
Classifier: Operating System :: OS Independent
Classifier: Programming Language :: Python :: 3
Requires-Python: >=3.7
